astroscript/AstroScript_background.webp
astroscript/__init__.py
astroscript/astroscript.py
astroscript/main.py
astroscript/mainmd.py
astroscript/save_event.py
astroscript/timezones.txt
astroscript/timezones_full.txt
astroscript/version.py
astroscript/ephe/astlistn.md
astroscript/ephe/astrologically_known_fixed_stars.txt
astroscript/ephe/fixed_stars_all.txt
astroscript/ephe/seas_18.se1
astroscript/ephe/sefstars.txt
astroscript/font/LICENSE.txt
astroscript/font/RobotoMono-Regular.ttf
astroscript/font/__init__.py
AstroScript-1.0.4.dist-info/METADATA
AstroScript-1.0.4.dist-info/WHEEL
AstroScript-1.0.4.dist-info/entry_points.txt
AstroScript-1.0.4.dist-info/top_level.txt
AstroScript-1.0.4.dist-info/RECORD
