Metadata-Version: 2.1
Name: AstroScript
Version: 1.0.4
Summary: Astrological calculation tool
Home-page: https://github.com/Shoresh613/astro-script/
Author: Mikael Folkesson
Author-email: mikael.folkesson@gmail.com
Project-URL: Bug Reports, https://github.com/Shoresh613/astro_script/issues
Project-URL: Source, https://github.com/Shoresh613/astro_script/
Keywords: astrology,horoscopes,charts
Classifier: Development Status :: 3 - Alpha
Classifier: Intended Audience :: End Users/Desktop
Classifier: Topic :: Utilities
Classifier: License :: OSI Approved :: MIT License
Classifier: Programming Language :: Python :: 3
Classifier: Programming Language :: Python :: 3.6
Classifier: Programming Language :: Python :: 3.7
Classifier: Programming Language :: Python :: 3.8
Classifier: Programming Language :: Python :: 3.9
Classifier: Programming Language :: Python :: 3.10
Requires-Python: >=3.6
Requires-Dist: pytz
Requires-Dist: pyswisseph
Requires-Dist: geopy
Requires-Dist: tabulate
